easy_pay/__init__.py
easy_pay/ali_pay.py
easy_pay/settings.py
easy_pay/wechat_pay.py
test/__init__.py
test/test_alipay.py
test/test_wechat_pay.py
easy_pay-0.1.4.dist-info/METADATA
easy_pay-0.1.4.dist-info/WHEEL
easy_pay-0.1.4.dist-info/top_level.txt
easy_pay-0.1.4.dist-info/RECORD
